odoo8_addon_datetime_formatter-8.0.1.0.0.99.dev12-py2.7-nspkg.pth
odoo8_addon_datetime_formatter-8.0.1.0.0.99.dev12.dist-info/DESCRIPTION.rst
odoo8_addon_datetime_formatter-8.0.1.0.0.99.dev12.dist-info/METADATA
odoo8_addon_datetime_formatter-8.0.1.0.0.99.dev12.dist-info/RECORD
odoo8_addon_datetime_formatter-8.0.1.0.0.99.dev12.dist-info/WHEEL
odoo8_addon_datetime_formatter-8.0.1.0.0.99.dev12.dist-info/metadata.json
odoo8_addon_datetime_formatter-8.0.1.0.0.99.dev12.dist-info/namespace_packages.txt
odoo8_addon_datetime_formatter-8.0.1.0.0.99.dev12.dist-info/top_level.txt
odoo_addons/datetime_formatter/README.rst
odoo_addons/datetime_formatter/__init__.py
odoo_addons/datetime_formatter/__openerp__.py
odoo_addons/datetime_formatter/exceptions.py
odoo_addons/datetime_formatter/models.py
odoo_addons/datetime_formatter/i18n/ca.po
odoo_addons/datetime_formatter/i18n/datetime_formatter.pot
odoo_addons/datetime_formatter/i18n/de.po
odoo_addons/datetime_formatter/i18n/es.po
odoo_addons/datetime_formatter/i18n/fr.po
odoo_addons/datetime_formatter/i18n/it.po
odoo_addons/datetime_formatter/i18n/sl.po
odoo_addons/datetime_formatter/i18n/tr.po
odoo_addons/datetime_formatter/static/description/icon.png
odoo_addons/datetime_formatter/tests/__init__.py
odoo_addons/datetime_formatter/tests/test_best_matcher.py
odoo_addons/datetime_formatter/tests/test_formatter.py
